Musica/Musica.py
Musica/__init__.py
Musica_A-1.0.0.dist-info/LICENSE.txt
Musica_A-1.0.0.dist-info/METADATA
Musica_A-1.0.0.dist-info/WHEEL
Musica_A-1.0.0.dist-info/top_level.txt
Musica_A-1.0.0.dist-info/RECORD
