Metadata-Version: 2.1
Name: Musica-A
Version: 1.0.0
Summary: play music with gui
Home-page: https://github.com/Antoino0704
Author: Antonino Buscarino
Author-email: fifaanto17@gmail.com
License: UNKNOWN
Project-URL: Bug Tracker, https://github.com/Antoino0704/Musica
Platform: UNKNOWN
Classifier: Programming Language :: Python :: 3
Classifier: License :: OSI Approved :: GNU General Public License v3 or later (GPLv3+)
Classifier: Operating System :: OS Independent
Requires-Python: >=3.8
